{
  "main": {
    "id": "a415441ee010a5c5",
    "type": "split",
    "children": [
      {
        "id": "9c8aa0931a8de8ff",
        "type": "tabs",
        "children": [
          {
            "id": "ada68d3cbc1e3bd9",
            "type": "leaf",
            "state": {
              "type": "empty",
              "state": {},
              "icon": "lucide-file",
              "title": "New tab"
            }
          }
        ]
      }
    ],
    "direction": "vertical"
  },
  "left": {
    "id": "990d992bbeb40cbb",
    "type": "split",
    "children": [
      {
        "id": "9872d8749f6ceb46",
        "type": "tabs",
        "children": [
          {
            "id": "d1c0d21067f8fdaf",
            "type": "leaf",
            "state": {
              "type": "file-explorer",
              "state": {
                "sortOrder": "alphabetical",
                "autoReveal": false
              },
              "icon": "lucide-folder-closed",
              "title": "Files"
            }
          },
          {
            "id": "2ed0e6007239342a",
            "type": "leaf",
            "state": {
              "type": "search",
              "state": {
                "query": "",
                "matchingCase": false,
                "explainSearch": false,
                "collapseAll": false,
                "extraContext": false,
                "sortOrder": "alphabetical"
              },
              "icon": "lucide-search",
              "title": "Search"
            }
          },
          {
            "id": "e63a5f1aac08706a",
            "type": "leaf",
            "state": {
              "type": "bookmarks",
              "state": {},
              "icon": "lucide-bookmark",
              "title": "Bookmarks"
            }
          }
        ]
      }
    ],
    "direction": "horizontal",
    "width": 300
  },
  "right": {
    "id": "b4181b98fe7b2084",
    "type": "split",
    "children": [
      {
        "id": "17102bc69ff23ef0",
        "type": "tabs",
        "children": [
          {
            "id": "e7ba3b7a52801e86",
            "type": "leaf",
            "state": {
              "type": "backlink",
              "state": {
                "collapseAll": false,
                "extraContext": false,
                "sortOrder": "alphabetical",
                "showSearch": false,
                "searchQuery": "",
                "backlinkCollapsed": false,
                "unlinkedCollapsed": true
              },
              "icon": "links-coming-in",
              "title": "Backlinks"
            }
          },
          {
            "id": "ffa4475525907110",
            "type": "leaf",
            "state": {
              "type": "outgoing-link",
              "state": {
                "linksCollapsed": false,
                "unlinkedCollapsed": true
              },
              "icon": "links-going-out",
              "title": "Outgoing links"
            }
          },
          {
            "id": "924ad00b299bc6fa",
            "type": "leaf",
            "state": {
              "type": "tag",
              "state": {
                "sortOrder": "frequency",
                "useHierarchy": true,
                "showSearch": false,
                "searchQuery": ""
              },
              "icon": "lucide-tags",
              "title": "Tags"
            }
          },
          {
            "id": "b777875830149774",
            "type": "leaf",
            "state": {
              "type": "all-properties",
              "state": {
                "sortOrder": "frequency",
                "showSearch": false,
                "searchQuery": ""
              },
              "icon": "lucide-archive",
              "title": "All properties"
            }
          },
          {
            "id": "70a1268257bc2afc",
            "type": "leaf",
            "state": {
              "type": "outline",
              "state": {
                "file": "Untitled.md",
                "followCursor": false,
                "showSearch": false,
                "searchQuery": ""
              },
              "icon": "lucide-list",
              "title": "Outline of Untitled"
            }
          }
        ]
      }
    ],
    "direction": "horizontal",
    "width": 300,
    "collapsed": true
  },
  "left-ribbon": {
    "hiddenItems": {
      "switcher:Open quick switcher": false,
      "graph:Open graph view": false,
      "canvas:Create new canvas": false,
      "daily-notes:Open today's daily note": false,
      "templates:Insert template": false,
      "command-palette:Open command palette": false,
      "bases:Create new base": false,
      "marp-slides:Show Slide Preview": false
    }
  },
  "active": "ada68d3cbc1e3bd9",
  "lastOpenFiles": [
    "log.md.tmp.506370.1776405244613",
    "index.md.tmp.506370.1776405238876",
    "wiki/queries/research-b3-prompt-sensitivity.md",
    "wiki/queries/research-b3-prompt-sensitivity.md.tmp.506370.1776405232890",
    "log.md.tmp.506370.1776404599188",
    "index.md.tmp.506370.1776404588741",
    "wiki/queries/research-topics-feasible.md.tmp.506370.1776404576315",
    "transformer-architecture.html.tmp.506370.1776394844065",
    "transformer-architecture.html.tmp.506370.1776394838960",
    "transformer-architecture.html.tmp.506370.1776394833907",
    "transformer-architecture.html.tmp.506370.1776394828252",
    "transformer-architecture.html.tmp.506370.1776394824461",
    "node_modules/pptxgenjs/README.md",
    "node_modules/jszip/graph.svg",
    "node_modules/jszip/sponsors.md",
    "node_modules/jszip/CHANGES.md",
    "node_modules/pako/README.md",
    "node_modules/pako/CHANGELOG.md",
    "node_modules/image-size/Readme.md",
    "node_modules/readable-stream/README.md",
    "node_modules/readable-stream/GOVERNANCE.md",
    "node_modules/readable-stream/CONTRIBUTING.md",
    "node_modules/readable-stream/doc/wg-meetings/2015-01-30.md",
    "node_modules/lie/README.md",
    "node_modules/util-deprecate/History.md",
    "node_modules/inherits/README.md",
    "node_modules/safe-buffer/README.md",
    "node_modules/core-util-is/README.md",
    "node_modules/queue/readme.md",
    "node_modules/process-nextick-args/readme.md",
    "node_modules/string_decoder/README.md",
    "node_modules/undici-types/README.md",
    "node_modules/process-nextick-args/license.md",
    "node_modules/isarray/README.md",
    "node_modules/@types/node/README.md",
    "node_modules/lie/license.md",
    "node_modules/immediate/README.md",
    "Untitled 1.canvas",
    "Untitled.canvas"
  ]
}